api/__init__.py
api/api.py
api/config.py
api/websocket.py
models/__init__.py
models/chat_model.py
models/command_model.py
models/converter.py
models/get_model.py
models/report_model.py
models/save_model.py
routes/__init__.py
routes/api.py
routes/websocket.py
services/__init__.py
services/aliyun_service.py
services/common_utils.py
services/file_utils.py
services/mcp_service.py
services/requests_service.py
services/voice_translation_service.py
ai_cytx-0.1.0.dist-info/METADATA
ai_cytx-0.1.0.dist-info/WHEEL
ai_cytx-0.1.0.dist-info/top_level.txt
ai_cytx-0.1.0.dist-info/RECORD
