Metadata-Version: 2.4
Name: ai-cytx
Version: 0.1.0
Summary: Add your description here
Home-page: 
Author: lz_lazy
Author-email: lz_lazy@163.com
Requires-Python: >=3.12
Requires-Dist: alibabacloud-bailian20231229==2.0.7
Requires-Dist: dashscope>=1.23.3
Requires-Dist: deepmerge>=2.0
Requires-Dist: dotenv>=0.9.9
Requires-Dist: fastapi>=0.115.12
Requires-Dist: flask>=3.1.1
Requires-Dist: gevent>=25.5.1
Requires-Dist: gevent-websocket>=0.10.1
Requires-Dist: gunicorn>=23.0.0
Requires-Dist: mcp[cli]>=1.8.1
Requires-Dist: requests>=2.32.3
Requires-Dist: setuptools>=80.9.0
Requires-Dist: sse-starlette>=2.3.5
Requires-Dist: twine>=6.1.0
Requires-Dist: uvicorn>=0.34.2
Requires-Dist: websockets>=15.0.1
Requires-Dist: wheel>=0.45.1
Dynamic: author
Dynamic: author-email
Dynamic: requires-python
